talos_loader/__init__.py
talos_loader/cli.py
talos_loader/src/__init__.py
talos_loader/src/loader.py
talos_loader/src/schema.py
talos_loader/templates/README.md.j2
talos_loader/templates/__init__.py
talos_loader/templates/check.py.j2
talos_loader/templates/dry_run.py.j2
talos_loader/templates/init.py.j2
talos_loader/templates/loaders_init.py.j2
talos_loader/templates/my_custom_loaders.py.j2
talos_loader/templates/pyproject.toml.j2
talos_loader-0.0.3.dist-info/METADATA
talos_loader-0.0.3.dist-info/WHEEL
talos_loader-0.0.3.dist-info/entry_points.txt
talos_loader-0.0.3.dist-info/top_level.txt
talos_loader-0.0.3.dist-info/RECORD
