Metadata-Version: 2.4
Name: talos-loader
Version: 0.0.3
Summary: A tool for creating and managing loader projects
Author: Your Name
Author-email: your.email@example.com
License: MIT
Classifier: Programming Language :: Python :: 3
Classifier: Programming Language :: Python :: 3.10
Classifier: Operating System :: OS Independent
Requires-Python: >=3.10
Requires-Dist: click<9.0.0,>=8.1.3
Requires-Dist: inquirer<4.0.0,>=3.1.3
Requires-Dist: jinja2<4.0.0,>=3.1.2
Requires-Dist: pydantic<3.0.0,>=2.0.0
Requires-Dist: talos-aclient==1.6.0
Dynamic: author
Dynamic: author-email
Dynamic: classifier
Dynamic: description
Dynamic: description-content-type
Dynamic: license
Dynamic: requires-dist
Dynamic: requires-python
Dynamic: summary
